pr0cks/__init__.py
pr0cks/console.py
pr0cks/server.py
pr0cks-0.2.1.dist-info/entry_points.txt
pr0cks-0.2.1.dist-info/LICENSE
pr0cks-0.2.1.dist-info/WHEEL
pr0cks-0.2.1.dist-info/METADATA
pr0cks-0.2.1.dist-info/RECORD
