Metadata-Version: 2.1
Name: pr0cks
Version: 0.2.1
Summary: Transparent proxy in python
Home-page: https://gitlab.com/NamingThingsIsHard/net/pr0cks/pr0cks
License: GPL-3.0-or-later
Keywords: transparent proxy,linux,iptables
Author: Nicolas VERDIER
Author-email: contact@n1nj4.eu
Requires-Python: >=3.6,<4.0
Classifier: Development Status :: 3 - Alpha
Classifier: License :: OSI Approved :: GNU General Public License v3 or later (GPLv3+)
Classifier: Operating System :: POSIX
Classifier: Programming Language :: Python :: 3
Classifier: Programming Language :: Python :: 3.6
Classifier: Programming Language :: Python :: 3.7
Classifier: Programming Language :: Python :: 3.8
Classifier: Topic :: Internet :: Name Service (DNS)
Classifier: Topic :: Internet :: Proxy Servers
Classifier: Topic :: System :: Networking
Requires-Dist: PySocks (>=1.7.1,<2.0.0)
Requires-Dist: pr0cks-extension (>=0.1.0,<0.2.0)
Project-URL: Bug Tracker, https://gitlab.com/NamingThingsIsHard/net/pr0cks/pr0cks
Project-URL: Repository, https://gitlab.com/NamingThingsIsHard/net/pr0cks/pr0cks
